dbrlist/__init__.py
dbrlist-0.0.4.dist-info/METADATA
dbrlist-0.0.4.dist-info/WHEEL
dbrlist-0.0.4.dist-info/top_level.txt
dbrlist-0.0.4.dist-info/RECORD
